plugs_configuration/__init__.py
plugs_configuration/admin.py
plugs_configuration/apps.py
plugs_configuration/models.py
plugs_configuration/serializers.py
plugs_configuration/urls.py
plugs_configuration/views.py
plugs_configuration/migrations/0001_initial.py
plugs_configuration/migrations/0002_configuration_type.py
plugs_configuration/migrations/0003_configuration_user.py
plugs_configuration/migrations/0004_auto_20170824_1255.py
plugs_configuration/migrations/0005_auto_20170913_2206.py
plugs_configuration/migrations/0006_auto_20190408_1154.py
plugs_configuration/migrations/__init__.py
plugs_configuration/static/css/plugs_configuration.css
plugs_configuration/static/js/plugs_configuration.js
plugs_configuration/templates/plugs_configuration/base.html
plugs_configuration-0.2.3.dist-info/AUTHORS.rst
plugs_configuration-0.2.3.dist-info/LICENSE
plugs_configuration-0.2.3.dist-info/METADATA
plugs_configuration-0.2.3.dist-info/WHEEL
plugs_configuration-0.2.3.dist-info/top_level.txt
plugs_configuration-0.2.3.dist-info/RECORD
