Metadata-Version: 2.1
Name: plugs-configuration
Version: 0.2.3
Summary: User, internal and external configurations
Home-page: https://github.com/solocompt/plugs-configuration
Author: Solo
Author-email: geral@solo.com.pt
License: MIT
Keywords: plugs-configuration
Platform: UNKNOWN
Classifier: Development Status :: 3 - Alpha
Classifier: Framework :: Django :: 1.11
Classifier: Intended Audience :: Developers
Classifier: License :: OSI Approved :: MIT License
Classifier: Natural Language :: English
Classifier: Programming Language :: Python :: 3
Requires-Dist: plugs-core (<1.0.0,>=0.1.7)
